excel2pyral/__init__.py
excel2pyral/excel_importer.py
excel2pyral/main.py
excel2pyral/pyuvm_generator.py
excel2pyral/systemrdl_compiler.py
excel2pyral/docs/README.md
excel2pyral/docs/README_api.md
excel2pyral/examples/PROJECT_TEST.rdl
excel2pyral/examples/PROJECT_TEST.xlsx
excel2pyral/examples/PROJECT_TEST_ral.py
excel2pyral/examples/mychip.rdl
excel2pyral/examples/mychip.xlsx
excel2pyral/examples/mychip_ral.py
excel2pyral-1.2.0.dist-info/licenses/LICENSE
excel2pyral-1.2.0.dist-info/METADATA
excel2pyral-1.2.0.dist-info/WHEEL
excel2pyral-1.2.0.dist-info/entry_points.txt
excel2pyral-1.2.0.dist-info/top_level.txt
excel2pyral-1.2.0.dist-info/RECORD
