Metadata-Version: 2.4
Name: excel2pyral
Version: 1.2.0
Summary: Convert Excel register specifications to PyUVM RAL models via SystemRDL
Home-page: https://github.com/SanCodex/excel2pyral
Author: Sanjay Singh
Author-email: Sanjay Singh <your.email@example.com>
License: MIT
Project-URL: Homepage, https://github.com/SanCodex/excel2pyral
Project-URL: Repository, https://github.com/SanCodex/excel2pyral
Project-URL: Issues, https://github.com/SanCodex/excel2pyral/issues
Keywords: SystemRDL,PyUVM,RAL,Register,Excel,UVM
Classifier: Development Status :: 4 - Beta
Classifier: Intended Audience :: Developers
Classifier: License :: OSI Approved :: MIT License
Classifier: Programming Language :: Python :: 3
Classifier: Programming Language :: Python :: 3.8
Classifier: Programming Language :: Python :: 3.9
Classifier: Programming Language :: Python :: 3.10
Classifier: Programming Language :: Python :: 3.11
Classifier: Topic :: Software Development :: Code Generators
Classifier: Topic :: Scientific/Engineering :: Electronic Design Automation (EDA)
Requires-Python: >=3.6
License-File: LICENSE
Requires-Dist: systemrdl-compiler>=1.27.0
Requires-Dist: pyuvm>=2.8.0
Requires-Dist: pandas>=1.3.0
Requires-Dist: openpyxl>=3.0.0
Provides-Extra: dev
Requires-Dist: pytest>=6.0; extra == "dev"
Requires-Dist: pytest-cov; extra == "dev"
Requires-Dist: black; extra == "dev"
Requires-Dist: flake8; extra == "dev"
Requires-Dist: mypy; extra == "dev"
Dynamic: author
Dynamic: home-page
Dynamic: license-file
Dynamic: requires-python
